moderation/__init__.py
moderation/admin.py
moderation/apps.py
moderation/constants.py
moderation/db.py
moderation/diff.py
moderation/fields.py
moderation/filterspecs.py
moderation/forms.py
moderation/helpers.py
moderation/managers.py
moderation/message_backends.py
moderation/models.py
moderation/moderator.py
moderation/queryset.py
moderation/register.py
moderation/signals.py
moderation/utils.py
moderation/conf/__init__.py
moderation/conf/settings.py
moderation/fixtures/test_moderation.json
moderation/fixtures/test_users.json
moderation/locale/de/LC_MESSAGES/django.mo
moderation/locale/de/LC_MESSAGES/django.po
moderation/locale/fr/LC_MESSAGES/django.mo
moderation/locale/fr/LC_MESSAGES/django.po
moderation/locale/he/LC_MESSAGES/django.mo
moderation/locale/he/LC_MESSAGES/django.po
moderation/locale/pt_BR/LC_MESSAGES/django.mo
moderation/locale/pt_BR/LC_MESSAGES/django.po
moderation/migrations/0001_initial.py
moderation/migrations/0002_auto_20150515_1057.py
moderation/migrations/0003_rename_fields_to_be_shorter.py
moderation/migrations/0004_auto_20180918_1132.py
moderation/migrations/0005_auto_20190412_0442.py
moderation/migrations/__init__.py
moderation/templates/moderation/html_diff.html
moderation/templates/moderation/image_diff.html
moderation/templates/moderation/moderate_object.html
moderation/templates/moderation/moderated_objects_list.html
moderation/templates/moderation/notification_message_moderator.txt
moderation/templates/moderation/notification_message_user.txt
moderation/templates/moderation/notification_subject_moderator.txt
moderation/templates/moderation/notification_subject_user.txt
django_moderation-0.8.0.dist-info/LICENSE
django_moderation-0.8.0.dist-info/METADATA
django_moderation-0.8.0.dist-info/WHEEL
django_moderation-0.8.0.dist-info/top_level.txt
django_moderation-0.8.0.dist-info/RECORD
