Metadata-Version: 2.1
Name: django-moderation
Version: 0.8.0
Summary: Generic Django objects moderation application
Home-page: https://github.com/dominno/django-moderation
Author: Dominik Szopa
Author-email: dszopa@gmail.com
License: BSD
Keywords: django moderation models
Platform: UNKNOWN
Classifier: Development Status :: 4 - Beta
Classifier: Environment :: Web Environment
Classifier: Intended Audience :: Developers
Classifier: License :: OSI Approved :: BSD License
Classifier: Operating System :: OS Independent
Classifier: Programming Language :: Python :: 3
Classifier: Programming Language :: Python :: 3.6
Classifier: Programming Language :: Python :: 3.7
Classifier: Programming Language :: Python :: 3.8
Classifier: Programming Language :: Python :: 3.9
Classifier: Programming Language :: Python :: 3 :: Only
Classifier: Framework :: Django
Classifier: Framework :: Django :: 2.2
Classifier: Framework :: Django :: 3.1
Classifier: Framework :: Django :: 3.2
License-File: LICENSE
Requires-Dist: django (>=2.2)
